Metadata-Version: 2.1
Name: pexels-api-with-video-searches
Version: 1.0.1
Summary: Use Pexels API v1 with Python
Home-page: https://github.com/Voltaic314/pexels-api-custom-voltaic
Author: Logan Maupin
Author-email: lmaupin@arizona.edu
Keywords: pexels api images photos videos
Classifier: Programming Language :: Python
Classifier: License :: OSI Approved :: MIT License
Classifier: Operating System :: OS Independent
License-File: LICENSE
Requires-Dist: requests
